rekcurd_client/__init__.py
rekcurd_client/_project.py
rekcurd_client/_version.py
rekcurd_client/core/__init__.py
rekcurd_client/core/rekcurd_worker_client.py
rekcurd_client/logger/__init__.py
rekcurd_client/logger/logger_fluent.py
rekcurd_client/logger/logger_interface.py
rekcurd_client/logger/logger_jsonlogger.py
rekcurd_client/protobuf/__init__.py
rekcurd_client/protobuf/rekcurd_pb2.py
rekcurd_client/protobuf/rekcurd_pb2_grpc.py
rekcurd_client-1.0.1.dist-info/LICENSE
rekcurd_client-1.0.1.dist-info/METADATA
rekcurd_client-1.0.1.dist-info/WHEEL
rekcurd_client-1.0.1.dist-info/top_level.txt
rekcurd_client-1.0.1.dist-info/RECORD
