Metadata-Version: 2.1
Name: rekcurd-client
Version: 1.0.1
Summary: A Python gRPC client for Rekcurd.
Home-page: https://github.com/rekcurd/python-client
Author: Rekcurd team and contributors
Author-email: rekcurd.developers@gmail.com
License: Apache License Version 2.0
Keywords: Rekcurd,Kubernetes,Python client,gRPC
Platform: UNKNOWN
Classifier: Development Status :: 3 - Alpha
Classifier: Environment :: Web Environment
Classifier: Topic :: Software Development :: Libraries :: Application Frameworks
Classifier: Intended Audience :: Developers
Classifier: Intended Audience :: Information Technology
Classifier: License :: OSI Approved :: Apache Software License
Classifier: Operating System :: OS Independent
Classifier: Programming Language :: Python
Classifier: Programming Language :: Python :: 3
Classifier: Programming Language :: Python :: 3.6
Classifier: Programming Language :: Python :: 3.7
Requires-Dist: grpcio (>=1.22.0)
Requires-Dist: grpcio-tools (>=1.22.0)
Requires-Dist: fluent-logger (>=0.9.3)
Requires-Dist: python-json-logger (>=0.1.9)
